binomialExpansion.dll
main.py
binomialExpansion-1.0.dist-info/METADATA
binomialExpansion-1.0.dist-info/WHEEL
binomialExpansion-1.0.dist-info/top_level.txt
binomialExpansion-1.0.dist-info/RECORD
