Metadata-Version: 2.1
Name: binomialExpansion
Version: 1.0
Summary: Implementacja Dwumianu Newtona
